{
    "Ar36": {
        "error": 9.20069095780845,
        "error_type": "SEM",
        "filter_outliers_dict": {
            "filter_outliers": false,
            "iterations": 0,
            "std_devs": 0,
            "use_iqr_filtering": false,
            "use_standard_deviation_filtering": false
        },
        "fit": "linear",
        "fn": 750,
        "include_baseline_error": false,
        "n": 750,
        "outlier_excluded": [],
        "reviewed": true,
        "user_excluded": [],
        "value": 15663.748721508946
    },
    "Ar37": {
        "error": 2.5782575600323994e-07,
        "error_type": "SEM",
        "filter_outliers_dict": {
            "filter_outliers": false,
            "iterations": 0,
            "std_devs": 0,
            "use_iqr_filtering": false,
            "use_standard_deviation_filtering": false
        },
        "fit": "linear",
        "fn": 75,
        "include_baseline_error": false,
        "n": 75,
        "outlier_excluded": [],
        "reviewed": true,
        "user_excluded": [],
        "value": 0.00014883318714985967
    },
    "Ar38": {
        "error": 2.2957626308448205e-07,
        "error_type": "SEM",
        "filter_outliers_dict": {
            "filter_outliers": false,
            "iterations": 0,
            "std_devs": 0,
            "use_iqr_filtering": false,
            "use_standard_deviation_filtering": false
        },
        "fit": "linear",
        "fn": 75,
        "include_baseline_error": false,
        "n": 75,
        "outlier_excluded": [],
        "reviewed": true,
        "user_excluded": [],
        "value": 7.321642354672932e-05
    },
    "Ar39": {
        "error": 4.89722142046527e-07,
        "error_type": "SEM",
        "filter_outliers_dict": {
            "filter_outliers": false,
            "iterations": 0,
            "std_devs": 0,
            "use_iqr_filtering": false,
            "use_standard_deviation_filtering": false
        },
        "fit": "linear",
        "fn": 75,
        "include_baseline_error": false,
        "n": 75,
        "outlier_excluded": [],
        "reviewed": true,
        "user_excluded": [],
        "value": 0.0009380616374556297
    },
    "Ar40": {
        "error": 1.9911136738544193e-05,
        "error_type": "SEM",
        "filter_outliers_dict": {
            "filter_outliers": false,
            "iterations": 0,
            "std_devs": 0,
            "use_iqr_filtering": false,
            "use_standard_deviation_filtering": false
        },
        "fit": "linear",
        "fn": 75,
        "include_baseline_error": false,
        "n": 75,
        "outlier_excluded": [],
        "reviewed": true,
        "user_excluded": [],
        "value": 0.08127424048424373
    }
}